derevo/__init__.py
derevo/adjacency.py
derevo/combined.py
derevo/compatability.py
derevo/composition.py
derevo/optimal_resolution.py
derevo/prepare_polygons.py
derevo/territories.py
derevo/models/__init__.py
derevo/models/cohabitation.py
derevo/models/enumerations.py
derevo/models/global_territory.py
derevo/models/plants.py
derevo/models/territory.py
derevo-0.1.2.dist-info/METADATA
derevo-0.1.2.dist-info/WHEEL
derevo-0.1.2.dist-info/top_level.txt
derevo-0.1.2.dist-info/RECORD
