Metadata-Version: 2.1
Name: derevo
Version: 0.1.2
Summary: Collection of methods to generate stable plants collections based on their cohabitation and outer limitations
Author-email: Aleksander Antonov <asantonov@itmo.ru>, Aleksei Sokol <aasokol@itmo.ru>
License: MIT
Project-URL: Repository, https://github.com/egov-itmo/landscaping
Project-URL: Bug Tracker, https://github.com/egov-itmo/landscaping/issues
Classifier: Programming Language :: Python :: 3
Classifier: License :: OSI Approved :: MIT License
Classifier: Operating System :: OS Independent
Requires-Python: >=3.9
Requires-Dist: geopandas >=0.12.0
Requires-Dist: loguru >=0.6.0
Requires-Dist: matplotlib >=3.5
Requires-Dist: networkx >=3.1
Requires-Dist: numpy >=1.24.0
Requires-Dist: pandas >=1.5.0
Provides-Extra: dev
Requires-Dist: black >=22 ; extra == 'dev'
Requires-Dist: isort ; extra == 'dev'
Requires-Dist: pylint ; extra == 'dev'
Requires-Dist: pre-commit >=3.1 ; extra == 'dev'
Requires-Dist: pytest ; extra == 'dev'
Requires-Dist: pytest-cov ; extra == 'dev'
